argparse_pydantic/__init__.py
argparse_pydantic/app.py
argparse_pydantic/core.py
argparse_pydantic/helpers.py
argparse_pydantic/test_tools.py
argparse_pydantic/version.py
argparse_pydantic-0.1.5.dist-info/LICENSE
argparse_pydantic-0.1.5.dist-info/METADATA
argparse_pydantic-0.1.5.dist-info/WHEEL
argparse_pydantic-0.1.5.dist-info/top_level.txt
argparse_pydantic-0.1.5.dist-info/RECORD
